{
  "benchmarkVersion": 5,
  "generatedAt": "2026-06-12T18:13:45.470Z",
  "node": "v23.11.0",
  "gitSha": "357eeca",
  "environment": {
    "generatedAt": "2026-06-12T18:13:45.470Z",
    "node": "v23.11.0",
    "platform": "darwin arm64",
    "cpu": "Apple M1 Pro",
    "cpuCount": 10,
    "commit": "357eeca8465173f6a63b2f46246bc20fede49b91"
  },
  "results": [
    {
      "size": 5000,
      "scenario": "S1",
      "label": "stream ON, cache OFF, chunk ON",
      "oneShotMs": 0.20649409999999999,
      "appendWorkloadMs": 0.6207399166666836,
      "appendLineMs": 1.6804787499999208,
      "replaceParagraphMs": 0.20497899999999447,
      "lastMode": "chunked",
      "appendHits": 0,
      "chunkInfoOne": {
        "count": 4,
        "maxChunkChars": 8000,
        "maxChunkLines": 150,
        "globalStateFallbackDisabled": false
      },
      "chunkInfoAppendLast": {
        "count": 4,
        "maxChunkChars": 8000,
        "maxChunkLines": 150,
        "globalStateFallbackDisabled": false
      }
    },
    {
      "size": 5000,
      "scenario": "S2",
      "label": "stream ON, cache ON, chunk OFF",
      "oneShotMs": 0.15824444166666704,
      "appendWorkloadMs": 0.2719622500000061,
      "appendLineMs": 0.5191055000000375,
      "replaceParagraphMs": 0.1594478749999979,
      "lastMode": "full",
      "appendHits": 276,
      "chunkInfoOne": null,
      "chunkInfoAppendLast": null
    },
    {
      "size": 5000,
      "scenario": "S3",
      "label": "stream ON, cache ON, chunk ON",
      "oneShotMs": 0.20253229166666717,
      "appendWorkloadMs": 0.25266666666665094,
      "appendLineMs": 0.4448834999999747,
      "replaceParagraphMs": 0.19622399999998663,
      "lastMode": "chunked",
      "appendHits": 276,
      "chunkInfoOne": {
        "count": 4,
        "maxChunkChars": 8000,
        "maxChunkLines": 150,
        "globalStateFallbackDisabled": false
      },
      "chunkInfoAppendLast": {
        "count": 4,
        "maxChunkChars": 8000,
        "maxChunkLines": 150,
        "globalStateFallbackDisabled": false
      }
    },
    {
      "size": 5000,
      "scenario": "S4",
      "label": "stream OFF, chunk ON",
      "oneShotMs": 0.18452778333333317,
      "appendWorkloadMs": 0.5543639999999925,
      "appendLineMs": 1.5809692500000665,
      "replaceParagraphMs": 0.20349999999999113,
      "lastMode": "idle",
      "appendHits": 0,
      "chunkInfoOne": {
        "count": 4,
        "maxChunkChars": 8000,
        "maxChunkLines": 150,
        "globalStateFallbackDisabled": false
      },
      "chunkInfoAppendLast": {
        "count": 4,
        "maxChunkChars": 8000,
        "maxChunkLines": 150,
        "globalStateFallbackDisabled": false
      }
    },
    {
      "size": 5000,
      "scenario": "S5",
      "label": "stream OFF, chunk OFF",
      "oneShotMs": 0.15307570000000037,
      "appendWorkloadMs": 0.5322288333333158,
      "appendLineMs": 1.5256979999999771,
      "replaceParagraphMs": 0.16789562499998567,
      "lastMode": "idle",
      "appendHits": 0,
      "chunkInfoOne": null,
      "chunkInfoAppendLast": null
    },
    {
      "size": 5000,
      "scenario": "M1",
      "label": "markdown-it (baseline)",
      "oneShotMs": 0.16320659999999995,
      "appendWorkloadMs": 0.5380971666666596,
      "appendLineMs": 1.5385319999999183,
      "replaceParagraphMs": 0.24219250000004422,
      "lastMode": "n/a",
      "appendHits": 0,
      "chunkInfoOne": null,
      "chunkInfoAppendLast": null
    },
    {
      "size": 5000,
      "scenario": "E1",
      "label": "markdown-exit",
      "oneShotMs": 0.2142381916666674,
      "appendWorkloadMs": 0.7233579166666193,
      "appendLineMs": 2.1834272499999656,
      "replaceParagraphMs": 0.23885437499995987,
      "lastMode": "n/a",
      "appendHits": 0,
      "chunkInfoOne": null,
      "chunkInfoAppendLast": null
    },
    {
      "size": 5000,
      "scenario": "MM1",
      "label": "micromark (parse only)",
      "oneShotMs": 3.776476741666666,
      "appendWorkloadMs": 12.134638583333338,
      "appendLineMs": 34.59198899999956,
      "replaceParagraphMs": 3.538911374999998,
      "lastMode": "n/a",
      "appendHits": 0,
      "chunkInfoOne": null,
      "chunkInfoAppendLast": null
    },
    {
      "size": 5000,
      "scenario": "R1",
      "label": "remark (parse only)",
      "oneShotMs": 4.585137149999999,
      "appendWorkloadMs": 15.443080083333598,
      "appendLineMs": 43.36875175000023,
      "replaceParagraphMs": 4.648354249999784,
      "lastMode": "n/a",
      "appendHits": 0,
      "chunkInfoOne": null,
      "chunkInfoAppendLast": null
    },
    {
      "size": 20000,
      "scenario": "S2",
      "label": "stream ON, cache ON, chunk OFF",
      "oneShotMs": 0.6473298500000055,
      "appendWorkloadMs": 0.8699507999990601,
      "appendLineMs": 1.229937124998969,
      "replaceParagraphMs": 0.671340333333319,
      "lastMode": "full",
      "appendHits": 165,
      "chunkInfoOne": null,
      "chunkInfoAppendLast": null
    },
    {
      "size": 20000,
      "scenario": "S3",
      "label": "stream ON, cache ON, chunk ON",
      "oneShotMs": 0.7866201333333265,
      "appendWorkloadMs": 0.8986002000012376,
      "appendLineMs": 1.20232737500055,
      "replaceParagraphMs": 0.7712709999997667,
      "lastMode": "chunked",
      "appendHits": 165,
      "chunkInfoOne": {
        "count": 8,
        "maxChunkChars": 8000,
        "maxChunkLines": 233,
        "globalStateFallbackDisabled": false
      },
      "chunkInfoAppendLast": {
        "count": 8,
        "maxChunkChars": 8000,
        "maxChunkLines": 233,
        "globalStateFallbackDisabled": false
      }
    },
    {
      "size": 20000,
      "scenario": "S4",
      "label": "stream OFF, chunk ON",
      "oneShotMs": 0.7447291666666691,
      "appendWorkloadMs": 2.50347440000005,
      "appendLineMs": 6.925312749999421,
      "replaceParagraphMs": 0.786312416666533,
      "lastMode": "idle",
      "appendHits": 0,
      "chunkInfoOne": {
        "count": 8,
        "maxChunkChars": 8000,
        "maxChunkLines": 233,
        "globalStateFallbackDisabled": false
      },
      "chunkInfoAppendLast": {
        "count": 8,
        "maxChunkChars": 8000,
        "maxChunkLines": 233,
        "globalStateFallbackDisabled": false
      }
    },
    {
      "size": 20000,
      "scenario": "S5",
      "label": "stream OFF, chunk OFF",
      "oneShotMs": 0.6051055666666798,
      "appendWorkloadMs": 2.213408000000345,
      "appendLineMs": 5.972335000000612,
      "replaceParagraphMs": 0.6001145000001695,
      "lastMode": "idle",
      "appendHits": 0,
      "chunkInfoOne": null,
      "chunkInfoAppendLast": null
    },
    {
      "size": 20000,
      "scenario": "M1",
      "label": "markdown-it (baseline)",
      "oneShotMs": 0.6591861000000184,
      "appendWorkloadMs": 2.2672926000010194,
      "appendLineMs": 6.157947749998584,
      "replaceParagraphMs": 0.6739549166666924,
      "lastMode": "n/a",
      "appendHits": 0,
      "chunkInfoOne": null,
      "chunkInfoAppendLast": null
    },
    {
      "size": 20000,
      "scenario": "E1",
      "label": "markdown-exit",
      "oneShotMs": 0.8832507000000078,
      "appendWorkloadMs": 3.036908000000403,
      "appendLineMs": 8.401203749997876,
      "replaceParagraphMs": 0.9178714999999709,
      "lastMode": "n/a",
      "appendHits": 0,
      "chunkInfoOne": null,
      "chunkInfoAppendLast": null
    },
    {
      "size": 20000,
      "scenario": "MM1",
      "label": "micromark (parse only)",
      "oneShotMs": 16.648131250000006,
      "appendWorkloadMs": 56.52115820000036,
      "appendLineMs": 149.57530712500102,
      "replaceParagraphMs": 16.9025555833338,
      "lastMode": "n/a",
      "appendHits": 0,
      "chunkInfoOne": null,
      "chunkInfoAppendLast": null
    },
    {
      "size": 20000,
      "scenario": "R1",
      "label": "remark (parse only)",
      "oneShotMs": 21.43834235000001,
      "appendWorkloadMs": 70.73313340000095,
      "appendLineMs": 196.948119374998,
      "replaceParagraphMs": 23.493218916666894,
      "lastMode": "n/a",
      "appendHits": 0,
      "chunkInfoOne": null,
      "chunkInfoAppendLast": null
    },
    {
      "size": 20000,
      "scenario": "S1",
      "label": "stream ON, cache OFF, chunk ON",
      "oneShotMs": 0.8940527833333666,
      "appendWorkloadMs": 2.6815915999977733,
      "appendLineMs": 7.303239374998611,
      "replaceParagraphMs": 0.778392250000555,
      "lastMode": "chunked",
      "appendHits": 0,
      "chunkInfoOne": {
        "count": 8,
        "maxChunkChars": 8000,
        "maxChunkLines": 233,
        "globalStateFallbackDisabled": false
      },
      "chunkInfoAppendLast": {
        "count": 8,
        "maxChunkChars": 8000,
        "maxChunkLines": 233,
        "globalStateFallbackDisabled": false
      }
    },
    {
      "size": 50000,
      "scenario": "S3",
      "label": "stream ON, cache ON, chunk ON",
      "oneShotMs": 2.051684733333362,
      "appendWorkloadMs": 2.1575473749990124,
      "appendLineMs": 2.656172833335707,
      "replaceParagraphMs": 1.9930791000009775,
      "lastMode": "chunked",
      "appendHits": 146,
      "chunkInfoOne": {
        "count": 8,
        "maxChunkChars": 8000,
        "maxChunkLines": 577,
        "globalStateFallbackDisabled": false
      },
      "chunkInfoAppendLast": {
        "count": 8,
        "maxChunkChars": 8000,
        "maxChunkLines": 577,
        "globalStateFallbackDisabled": false
      }
    },
    {
      "size": 50000,
      "scenario": "S4",
      "label": "stream OFF, chunk ON",
      "oneShotMs": 1.9636986333333577,
      "appendWorkloadMs": 6.404594124998766,
      "appendLineMs": 17.485555833335944,
      "replaceParagraphMs": 1.8882414000014252,
      "lastMode": "idle",
      "appendHits": 0,
      "chunkInfoOne": {
        "count": 8,
        "maxChunkChars": 8000,
        "maxChunkLines": 576,
        "globalStateFallbackDisabled": false
      },
      "chunkInfoAppendLast": {
        "count": 8,
        "maxChunkChars": 8000,
        "maxChunkLines": 577,
        "globalStateFallbackDisabled": false
      }
    },
    {
      "size": 50000,
      "scenario": "S5",
      "label": "stream OFF, chunk OFF",
      "oneShotMs": 1.5615403000001,
      "appendWorkloadMs": 5.5787343749971114,
      "appendLineMs": 15.146139333330211,
      "replaceParagraphMs": 1.5112835000014457,
      "lastMode": "idle",
      "appendHits": 0,
      "chunkInfoOne": null,
      "chunkInfoAppendLast": null
    },
    {
      "size": 50000,
      "scenario": "M1",
      "label": "markdown-it (baseline)",
      "oneShotMs": 1.6504514000000199,
      "appendWorkloadMs": 5.590542124997228,
      "appendLineMs": 15.304402166663447,
      "replaceParagraphMs": 1.6921291000006022,
      "lastMode": "n/a",
      "appendHits": 0,
      "chunkInfoOne": null,
      "chunkInfoAppendLast": null
    },
    {
      "size": 50000,
      "scenario": "E1",
      "label": "markdown-exit",
      "oneShotMs": 2.271576400000049,
      "appendWorkloadMs": 7.426744624997809,
      "appendLineMs": 20.28693833334061,
      "replaceParagraphMs": 2.1780333000002425,
      "lastMode": "n/a",
      "appendHits": 0,
      "chunkInfoOne": null,
      "chunkInfoAppendLast": null
    },
    {
      "size": 50000,
      "scenario": "MM1",
      "label": "micromark (parse only)",
      "oneShotMs": 44.96880280000017,
      "appendWorkloadMs": 152.05219837499772,
      "appendLineMs": 411.1130824999964,
      "replaceParagraphMs": 44.46362099999824,
      "lastMode": "n/a",
      "appendHits": 0,
      "chunkInfoOne": null,
      "chunkInfoAppendLast": null
    },
    {
      "size": 50000,
      "scenario": "R1",
      "label": "remark (parse only)",
      "oneShotMs": 60.5528694333334,
      "appendWorkloadMs": 197.06983312500233,
      "appendLineMs": 578.3638676666694,
      "replaceParagraphMs": 62.39930850000091,
      "lastMode": "n/a",
      "appendHits": 0,
      "chunkInfoOne": null,
      "chunkInfoAppendLast": null
    },
    {
      "size": 50000,
      "scenario": "S1",
      "label": "stream ON, cache OFF, chunk ON",
      "oneShotMs": 2.0610722333333493,
      "appendWorkloadMs": 6.771390625010099,
      "appendLineMs": 18.334208833335047,
      "replaceParagraphMs": 2.0315417999998315,
      "lastMode": "chunked",
      "appendHits": 0,
      "chunkInfoOne": {
        "count": 8,
        "maxChunkChars": 8000,
        "maxChunkLines": 577,
        "globalStateFallbackDisabled": false
      },
      "chunkInfoAppendLast": {
        "count": 8,
        "maxChunkChars": 8000,
        "maxChunkLines": 577,
        "globalStateFallbackDisabled": false
      }
    },
    {
      "size": 50000,
      "scenario": "S2",
      "label": "stream ON, cache ON, chunk OFF",
      "oneShotMs": 1.6419916666670664,
      "appendWorkloadMs": 2.073453375000099,
      "appendLineMs": 2.6182491666719825,
      "replaceParagraphMs": 1.5487793999971473,
      "lastMode": "full",
      "appendHits": 146,
      "chunkInfoOne": null,
      "chunkInfoAppendLast": null
    },
    {
      "size": 100000,
      "scenario": "S4",
      "label": "stream OFF, chunk ON",
      "oneShotMs": 4.5375025625007765,
      "appendWorkloadMs": 13.64127849999204,
      "appendLineMs": 35.988885749990004,
      "replaceParagraphMs": 3.82466137499614,
      "lastMode": "idle",
      "appendHits": 0,
      "chunkInfoOne": {
        "count": 8,
        "maxChunkChars": 12516,
        "maxChunkLines": 700,
        "globalStateFallbackDisabled": false
      },
      "chunkInfoAppendLast": {
        "count": 8,
        "maxChunkChars": 12518,
        "maxChunkLines": 700,
        "globalStateFallbackDisabled": false
      }
    },
    {
      "size": 100000,
      "scenario": "S5",
      "label": "stream OFF, chunk OFF",
      "oneShotMs": 4.035153625000021,
      "appendWorkloadMs": 12.283791333335103,
      "appendLineMs": 33.30418899999859,
      "replaceParagraphMs": 3.8491302499987796,
      "lastMode": "idle",
      "appendHits": 0,
      "chunkInfoOne": null,
      "chunkInfoAppendLast": null
    },
    {
      "size": 100000,
      "scenario": "M1",
      "label": "markdown-it (baseline)",
      "oneShotMs": 4.317302125000424,
      "appendWorkloadMs": 11.590368166672608,
      "appendLineMs": 31.15992650001499,
      "replaceParagraphMs": 3.6254167499992036,
      "lastMode": "n/a",
      "appendHits": 0,
      "chunkInfoOne": null,
      "chunkInfoAppendLast": null
    },
    {
      "size": 100000,
      "scenario": "E1",
      "label": "markdown-exit",
      "oneShotMs": 5.587791687500612,
      "appendWorkloadMs": 15.168875666672344,
      "appendLineMs": 42.61485475000882,
      "replaceParagraphMs": 4.75344799999948,
      "lastMode": "n/a",
      "appendHits": 0,
      "chunkInfoOne": null,
      "chunkInfoAppendLast": null
    },
    {
      "size": 100000,
      "scenario": "MM1",
      "label": "micromark (parse only)",
      "oneShotMs": 93.3391588125005,
      "appendWorkloadMs": 314.92063183334295,
      "appendLineMs": 862.8382709999787,
      "replaceParagraphMs": 90.28639575000125,
      "lastMode": "n/a",
      "appendHits": 0,
      "chunkInfoOne": null,
      "chunkInfoAppendLast": null
    },
    {
      "size": 100000,
      "scenario": "R1",
      "label": "remark (parse only)",
      "oneShotMs": 140.51584637499946,
      "appendWorkloadMs": 452.62046466666413,
      "appendLineMs": 1240.3910842500009,
      "replaceParagraphMs": 140.96844287500062,
      "lastMode": "n/a",
      "appendHits": 0,
      "chunkInfoOne": null,
      "chunkInfoAppendLast": null
    },
    {
      "size": 100000,
      "scenario": "S1",
      "label": "stream ON, cache OFF, chunk ON",
      "oneShotMs": 4.832531250000102,
      "appendWorkloadMs": 14.367479666657648,
      "appendLineMs": 38.12570800001049,
      "replaceParagraphMs": 4.096999625000535,
      "lastMode": "chunked",
      "appendHits": 0,
      "chunkInfoOne": {
        "count": 8,
        "maxChunkChars": 12518,
        "maxChunkLines": 700,
        "globalStateFallbackDisabled": false
      },
      "chunkInfoAppendLast": {
        "count": 8,
        "maxChunkChars": 12518,
        "maxChunkLines": 700,
        "globalStateFallbackDisabled": false
      }
    },
    {
      "size": 100000,
      "scenario": "S2",
      "label": "stream ON, cache ON, chunk OFF",
      "oneShotMs": 4.2794739999999365,
      "appendWorkloadMs": 4.642764333337254,
      "appendLineMs": 5.6712277499973425,
      "replaceParagraphMs": 3.5832291250007984,
      "lastMode": "full",
      "appendHits": 92,
      "chunkInfoOne": null,
      "chunkInfoAppendLast": null
    },
    {
      "size": 100000,
      "scenario": "S3",
      "label": "stream ON, cache ON, chunk ON",
      "oneShotMs": 4.8630703124999854,
      "appendWorkloadMs": 4.656721999994867,
      "appendLineMs": 5.638812249999319,
      "replaceParagraphMs": 3.9803383750004286,
      "lastMode": "chunked",
      "appendHits": 92,
      "chunkInfoOne": {
        "count": 8,
        "maxChunkChars": 12518,
        "maxChunkLines": 700,
        "globalStateFallbackDisabled": false
      },
      "chunkInfoAppendLast": {
        "count": 8,
        "maxChunkChars": 12518,
        "maxChunkLines": 700,
        "globalStateFallbackDisabled": false
      }
    },
    {
      "size": 200000,
      "scenario": "S5",
      "label": "stream OFF, chunk OFF",
      "oneShotMs": 10.312579200000618,
      "appendWorkloadMs": 26.438249499999074,
      "appendLineMs": 81.08110425000268,
      "replaceParagraphMs": 8.18717366666533,
      "lastMode": "idle",
      "appendHits": 0,
      "chunkInfoOne": null,
      "chunkInfoAppendLast": null
    },
    {
      "size": 200000,
      "scenario": "M1",
      "label": "markdown-it (baseline)",
      "oneShotMs": 9.240337499999441,
      "appendWorkloadMs": 25.067092999986926,
      "appendLineMs": 69.48847899998873,
      "replaceParagraphMs": 6.938708000001498,
      "lastMode": "n/a",
      "appendHits": 0,
      "chunkInfoOne": null,
      "chunkInfoAppendLast": null
    },
    {
      "size": 200000,
      "scenario": "E1",
      "label": "markdown-exit",
      "oneShotMs": 12.464362499999698,
      "appendWorkloadMs": 41.25713550000364,
      "appendLineMs": 89.91031274999114,
      "replaceParagraphMs": 9.666826499994688,
      "lastMode": "n/a",
      "appendHits": 0,
      "chunkInfoOne": null,
      "chunkInfoAppendLast": null
    },
    {
      "size": 200000,
      "scenario": "MM1",
      "label": "micromark (parse only)",
      "oneShotMs": 182.58938339999878,
      "appendWorkloadMs": 632.9090629999992,
      "appendLineMs": 1749.4811767499923,
      "replaceParagraphMs": 195.434083333336,
      "lastMode": "n/a",
      "appendHits": 0,
      "chunkInfoOne": null,
      "chunkInfoAppendLast": null
    },
    {
      "size": 200000,
      "scenario": "R1",
      "label": "remark (parse only)",
      "oneShotMs": 340.21916669999774,
      "appendWorkloadMs": 1246.5300520000092,
      "appendLineMs": 3139.304792750023,
      "replaceParagraphMs": 386.08423599999514,
      "lastMode": "n/a",
      "appendHits": 0,
      "chunkInfoOne": null,
      "chunkInfoAppendLast": null
    },
    {
      "size": 200000,
      "scenario": "S1",
      "label": "stream ON, cache OFF, chunk ON",
      "oneShotMs": 9.835920799997984,
      "appendWorkloadMs": 30.315458750003017,
      "appendLineMs": 84.40900025003793,
      "replaceParagraphMs": 7.971027833336848,
      "lastMode": "chunked",
      "appendHits": 0,
      "chunkInfoOne": {
        "count": 8,
        "maxChunkChars": 25012,
        "maxChunkLines": 700,
        "globalStateFallbackDisabled": false
      },
      "chunkInfoAppendLast": {
        "count": 8,
        "maxChunkChars": 25012,
        "maxChunkLines": 700,
        "globalStateFallbackDisabled": false
      }
    },
    {
      "size": 200000,
      "scenario": "S2",
      "label": "stream ON, cache ON, chunk OFF",
      "oneShotMs": 9.757391700000152,
      "appendWorkloadMs": 8.99617625000974,
      "appendLineMs": 13.163145749997057,
      "replaceParagraphMs": 10.168673499996657,
      "lastMode": "full",
      "appendHits": 72,
      "chunkInfoOne": null,
      "chunkInfoAppendLast": null
    },
    {
      "size": 200000,
      "scenario": "S3",
      "label": "stream ON, cache ON, chunk ON",
      "oneShotMs": 10.557366699998965,
      "appendWorkloadMs": 9.678760750015499,
      "appendLineMs": 11.088780999991286,
      "replaceParagraphMs": 8.188451333330402,
      "lastMode": "chunked",
      "appendHits": 72,
      "chunkInfoOne": {
        "count": 8,
        "maxChunkChars": 25012,
        "maxChunkLines": 700,
        "globalStateFallbackDisabled": false
      },
      "chunkInfoAppendLast": {
        "count": 8,
        "maxChunkChars": 25012,
        "maxChunkLines": 700,
        "globalStateFallbackDisabled": false
      }
    },
    {
      "size": 200000,
      "scenario": "S4",
      "label": "stream OFF, chunk ON",
      "oneShotMs": 10.148004200001015,
      "appendWorkloadMs": 30.969613500019477,
      "appendLineMs": 81.79798925000068,
      "replaceParagraphMs": 7.686624833329309,
      "lastMode": "idle",
      "appendHits": 0,
      "chunkInfoOne": {
        "count": 8,
        "maxChunkChars": 25010,
        "maxChunkLines": 700,
        "globalStateFallbackDisabled": false
      },
      "chunkInfoAppendLast": {
        "count": 8,
        "maxChunkChars": 25012,
        "maxChunkLines": 700,
        "globalStateFallbackDisabled": false
      }
    },
    {
      "size": 500000,
      "scenario": "M1",
      "label": "markdown-it (baseline)",
      "oneShotMs": 26.552947874999518,
      "appendWorkloadMs": 84.24220899995998,
      "appendLineMs": 234.56306149999727,
      "replaceParagraphMs": 25.46816674999718,
      "lastMode": "n/a",
      "appendHits": 0,
      "chunkInfoOne": null,
      "chunkInfoAppendLast": null
    },
    {
      "size": 500000,
      "scenario": "E1",
      "label": "markdown-exit",
      "oneShotMs": 31.838697999999567,
      "appendWorkloadMs": 99.22945899996557,
      "appendLineMs": 290.7004385000182,
      "replaceParagraphMs": 29.84990624999773,
      "lastMode": "n/a",
      "appendHits": 0,
      "chunkInfoOne": null,
      "chunkInfoAppendLast": null
    },
    {
      "size": 500000,
      "scenario": "S1",
      "label": "stream ON, cache OFF, chunk ON",
      "oneShotMs": 26.129593749999913,
      "appendWorkloadMs": 81.91616600003908,
      "appendLineMs": 239.97504199999094,
      "replaceParagraphMs": 25.059624999994412,
      "lastMode": "chunked",
      "appendHits": 0,
      "chunkInfoOne": {
        "count": 8,
        "maxChunkChars": 62518,
        "maxChunkLines": 700,
        "globalStateFallbackDisabled": false
      },
      "chunkInfoAppendLast": {
        "count": 8,
        "maxChunkChars": 62518,
        "maxChunkLines": 700,
        "globalStateFallbackDisabled": false
      }
    },
    {
      "size": 500000,
      "scenario": "S2",
      "label": "stream ON, cache ON, chunk OFF",
      "oneShotMs": 23.935838624998723,
      "appendWorkloadMs": 32.3790840000147,
      "appendLineMs": 31.740646499951254,
      "replaceParagraphMs": 24.17693750000035,
      "lastMode": "full",
      "appendHits": 31,
      "chunkInfoOne": null,
      "chunkInfoAppendLast": null
    },
    {
      "size": 500000,
      "scenario": "S3",
      "label": "stream ON, cache ON, chunk ON",
      "oneShotMs": 26.884077999999135,
      "appendWorkloadMs": 32.532124000019394,
      "appendLineMs": 30.649334500049008,
      "replaceParagraphMs": 29.57534375000978,
      "lastMode": "chunked",
      "appendHits": 31,
      "chunkInfoOne": {
        "count": 8,
        "maxChunkChars": 62518,
        "maxChunkLines": 700,
        "globalStateFallbackDisabled": false
      },
      "chunkInfoAppendLast": {
        "count": 8,
        "maxChunkChars": 62518,
        "maxChunkLines": 700,
        "globalStateFallbackDisabled": false
      }
    },
    {
      "size": 500000,
      "scenario": "S4",
      "label": "stream OFF, chunk ON",
      "oneShotMs": 26.92494799999986,
      "appendWorkloadMs": 84.4783339999849,
      "appendLineMs": 238.12120949992095,
      "replaceParagraphMs": 28.304760500002885,
      "lastMode": "idle",
      "appendHits": 0,
      "chunkInfoOne": {
        "count": 8,
        "maxChunkChars": 62516,
        "maxChunkLines": 700,
        "globalStateFallbackDisabled": false
      },
      "chunkInfoAppendLast": {
        "count": 8,
        "maxChunkChars": 62518,
        "maxChunkLines": 700,
        "globalStateFallbackDisabled": false
      }
    },
    {
      "size": 500000,
      "scenario": "S5",
      "label": "stream OFF, chunk OFF",
      "oneShotMs": 26.33835425000143,
      "appendWorkloadMs": 84.68983500005561,
      "appendLineMs": 243.98462499999732,
      "replaceParagraphMs": 25.667000249988632,
      "lastMode": "idle",
      "appendHits": 0,
      "chunkInfoOne": null,
      "chunkInfoAppendLast": null
    },
    {
      "size": 1000000,
      "scenario": "E1",
      "label": "markdown-exit",
      "oneShotMs": 64.8810000000085,
      "appendWorkloadMs": 232.3484575000184,
      "appendLineMs": 630.0526869999885,
      "replaceParagraphMs": 74.32129199999326,
      "lastMode": "n/a",
      "appendHits": 0,
      "chunkInfoOne": null,
      "chunkInfoAppendLast": null
    },
    {
      "size": 1000000,
      "scenario": "S1",
      "label": "stream ON, cache OFF, chunk ON",
      "oneShotMs": 50.515625,
      "appendWorkloadMs": 175.84981199998583,
      "appendLineMs": 505.0724595000502,
      "replaceParagraphMs": 63.86502050001582,
      "lastMode": "chunked",
      "appendHits": 0,
      "chunkInfoOne": {
        "count": 16,
        "maxChunkChars": 64000,
        "maxChunkLines": 700,
        "globalStateFallbackDisabled": false
      },
      "chunkInfoAppendLast": {
        "count": 16,
        "maxChunkChars": 64000,
        "maxChunkLines": 700,
        "globalStateFallbackDisabled": false
      }
    },
    {
      "size": 1000000,
      "scenario": "S2",
      "label": "stream ON, cache ON, chunk OFF",
      "oneShotMs": 58.931937500005006,
      "appendWorkloadMs": 74.7280630000023,
      "appendLineMs": 66.00791550004215,
      "replaceParagraphMs": 61.26239549998718,
      "lastMode": "full",
      "appendHits": 32,
      "chunkInfoOne": null,
      "chunkInfoAppendLast": null
    },
    {
      "size": 1000000,
      "scenario": "S3",
      "label": "stream ON, cache ON, chunk ON",
      "oneShotMs": 51.2063124999986,
      "appendWorkloadMs": 64.32885300001362,
      "appendLineMs": 77.65170800007763,
      "replaceParagraphMs": 65.65699950000271,
      "lastMode": "chunked",
      "appendHits": 32,
      "chunkInfoOne": {
        "count": 16,
        "maxChunkChars": 64000,
        "maxChunkLines": 700,
        "globalStateFallbackDisabled": false
      },
      "chunkInfoAppendLast": {
        "count": 16,
        "maxChunkChars": 64000,
        "maxChunkLines": 700,
        "globalStateFallbackDisabled": false
      }
    },
    {
      "size": 1000000,
      "scenario": "S4",
      "label": "stream OFF, chunk ON",
      "oneShotMs": 50.473916500021005,
      "appendWorkloadMs": 190.82247800001642,
      "appendLineMs": 492.8006034999562,
      "replaceParagraphMs": 54.695750000013504,
      "lastMode": "idle",
      "appendHits": 0,
      "chunkInfoOne": {
        "count": 16,
        "maxChunkChars": 64000,
        "maxChunkLines": 700,
        "globalStateFallbackDisabled": false
      },
      "chunkInfoAppendLast": {
        "count": 16,
        "maxChunkChars": 64000,
        "maxChunkLines": 700,
        "globalStateFallbackDisabled": false
      }
    },
    {
      "size": 1000000,
      "scenario": "S5",
      "label": "stream OFF, chunk OFF",
      "oneShotMs": 52.200166499998886,
      "appendWorkloadMs": 175.33070699998643,
      "appendLineMs": 508.02372900000773,
      "replaceParagraphMs": 49.537812499998836,
      "lastMode": "idle",
      "appendHits": 0,
      "chunkInfoOne": null,
      "chunkInfoAppendLast": null
    },
    {
      "size": 1000000,
      "scenario": "M1",
      "label": "markdown-it (baseline)",
      "oneShotMs": 50.04737500002375,
      "appendWorkloadMs": 185.26902100004372,
      "appendLineMs": 522.4200825000298,
      "replaceParagraphMs": 50.23106250001001,
      "lastMode": "n/a",
      "appendHits": 0,
      "chunkInfoOne": null,
      "chunkInfoAppendLast": null
    }
  ],
  "coldHot": [
    {
      "size": 5000,
      "id": "TS",
      "label": "markdown-it-ts (stream+chunk)",
      "type": "ts",
      "coldMs": 0.2132080000010319,
      "hotMs": 0.18507089999620802
    },
    {
      "size": 5000,
      "id": "MD",
      "label": "markdown-it (baseline)",
      "type": "md-original",
      "coldMs": 0.16608300001826137,
      "hotMs": 0.21440419999998994
    },
    {
      "size": 5000,
      "id": "MM",
      "label": "micromark (parse only)",
      "type": "micromark-parse",
      "coldMs": 4.0131669999682344,
      "hotMs": 3.5867290999973194
    },
    {
      "size": 5000,
      "id": "RM",
      "label": "remark (parse only)",
      "type": "remark",
      "coldMs": 4.020582999975886,
      "hotMs": 3.724024999997346
    },
    {
      "size": 5000,
      "id": "EX",
      "label": "markdown-exit",
      "type": "md-exit",
      "coldMs": 0.22379099996760488,
      "hotMs": 0.2108834000013303
    },
    {
      "size": 20000,
      "id": "TS",
      "label": "markdown-it-ts (stream+chunk)",
      "type": "ts",
      "coldMs": 0.786374999966938,
      "hotMs": 0.7862542000017129
    },
    {
      "size": 20000,
      "id": "MD",
      "label": "markdown-it (baseline)",
      "type": "md-original",
      "coldMs": 0.631915999983903,
      "hotMs": 0.654812499997206
    },
    {
      "size": 20000,
      "id": "MM",
      "label": "micromark (parse only)",
      "type": "micromark-parse",
      "coldMs": 16.321042000025045,
      "hotMs": 16.60619580000057
    },
    {
      "size": 20000,
      "id": "RM",
      "label": "remark (parse only)",
      "type": "remark",
      "coldMs": 21.739750000007916,
      "hotMs": 21.31311660000356
    },
    {
      "size": 20000,
      "id": "EX",
      "label": "markdown-exit",
      "type": "md-exit",
      "coldMs": 0.8416670000297017,
      "hotMs": 0.8684499999973923
    },
    {
      "size": 50000,
      "id": "TS",
      "label": "markdown-it-ts (stream+chunk)",
      "type": "ts",
      "coldMs": 1.8831670000217855,
      "hotMs": 2.0459375000034923
    },
    {
      "size": 50000,
      "id": "MD",
      "label": "markdown-it (baseline)",
      "type": "md-original",
      "coldMs": 1.552832999965176,
      "hotMs": 1.7234583000012207
    },
    {
      "size": 50000,
      "id": "MM",
      "label": "micromark (parse only)",
      "type": "micromark-parse",
      "coldMs": 40.776542000006884,
      "hotMs": 44.66843330000411
    },
    {
      "size": 50000,
      "id": "RM",
      "label": "remark (parse only)",
      "type": "remark",
      "coldMs": 68.70174999994924,
      "hotMs": 61.83058329999913
    },
    {
      "size": 50000,
      "id": "EX",
      "label": "markdown-exit",
      "type": "md-exit",
      "coldMs": 2.0582919999724254,
      "hotMs": 2.312154100002954
    },
    {
      "size": 100000,
      "id": "TS",
      "label": "markdown-it-ts (stream+chunk)",
      "type": "ts",
      "coldMs": 5.6265000000130385,
      "hotMs": 5.174008300004061
    },
    {
      "size": 100000,
      "id": "MD",
      "label": "markdown-it (baseline)",
      "type": "md-original",
      "coldMs": 4.250667000014801,
      "hotMs": 4.202725000004284
    },
    {
      "size": 100000,
      "id": "MM",
      "label": "micromark (parse only)",
      "type": "micromark-parse",
      "coldMs": 82.21249999996508,
      "hotMs": 89.15582909999648
    },
    {
      "size": 100000,
      "id": "RM",
      "label": "remark (parse only)",
      "type": "remark",
      "coldMs": 132.59166599996388,
      "hotMs": 132.90110420000275
    },
    {
      "size": 100000,
      "id": "EX",
      "label": "markdown-exit",
      "type": "md-exit",
      "coldMs": 5.009458000015002,
      "hotMs": 5.205604200001107
    }
  ],
  "renderComparisons": [
    {
      "size": 5000,
      "scenario": "TS_RENDER",
      "label": "markdown-it-ts.render",
      "renderMs": 0.1703861083330897
    },
    {
      "size": 5000,
      "scenario": "MD_RENDER",
      "label": "markdown-it.render",
      "renderMs": 0.19835694166686152
    },
    {
      "size": 5000,
      "scenario": "MM_RENDER",
      "label": "micromark (CommonMark)",
      "renderMs": 3.6142263916670343
    },
    {
      "size": 5000,
      "scenario": "RM_RENDER",
      "label": "remark+rehype",
      "renderMs": 4.184375349999755
    },
    {
      "size": 5000,
      "scenario": "EX_RENDER",
      "label": "markdown-exit",
      "renderMs": 0.25548020833327123
    },
    {
      "size": 20000,
      "scenario": "MD_RENDER",
      "label": "markdown-it.render",
      "renderMs": 0.8030409666661096
    },
    {
      "size": 20000,
      "scenario": "MM_RENDER",
      "label": "micromark (CommonMark)",
      "renderMs": 20.366471533332756
    },
    {
      "size": 20000,
      "scenario": "RM_RENDER",
      "label": "remark+rehype",
      "renderMs": 24.18581388333308
    },
    {
      "size": 20000,
      "scenario": "EX_RENDER",
      "label": "markdown-exit",
      "renderMs": 1.029040283333355
    },
    {
      "size": 20000,
      "scenario": "TS_RENDER",
      "label": "markdown-it-ts.render",
      "renderMs": 0.6834527833329048
    },
    {
      "size": 50000,
      "scenario": "MM_RENDER",
      "label": "micromark (CommonMark)",
      "renderMs": 52.94244583333493
    },
    {
      "size": 50000,
      "scenario": "RM_RENDER",
      "label": "remark+rehype",
      "renderMs": 71.54876943333268
    },
    {
      "size": 50000,
      "scenario": "EX_RENDER",
      "label": "markdown-exit",
      "renderMs": 2.655180566666725
    },
    {
      "size": 50000,
      "scenario": "TS_RENDER",
      "label": "markdown-it-ts.render",
      "renderMs": 1.8345361000004534
    },
    {
      "size": 50000,
      "scenario": "MD_RENDER",
      "label": "markdown-it.render",
      "renderMs": 2.0314402999996672
    },
    {
      "size": 100000,
      "scenario": "RM_RENDER",
      "label": "remark+rehype",
      "renderMs": 150.11081249999916
    },
    {
      "size": 100000,
      "scenario": "EX_RENDER",
      "label": "markdown-exit",
      "renderMs": 6.791085937500611
    },
    {
      "size": 100000,
      "scenario": "TS_RENDER",
      "label": "markdown-it-ts.render",
      "renderMs": 4.90166143749957
    },
    {
      "size": 100000,
      "scenario": "MD_RENDER",
      "label": "markdown-it.render",
      "renderMs": 5.429158812501555
    },
    {
      "size": 100000,
      "scenario": "MM_RENDER",
      "label": "micromark (CommonMark)",
      "renderMs": 105.55135937500017
    },
    {
      "size": 200000,
      "scenario": "EX_RENDER",
      "label": "markdown-exit",
      "renderMs": 15.682925000000978
    },
    {
      "size": 200000,
      "scenario": "TS_RENDER",
      "label": "markdown-it-ts.render",
      "renderMs": 10.910833299998194
    },
    {
      "size": 200000,
      "scenario": "MD_RENDER",
      "label": "markdown-it.render",
      "renderMs": 12.996216699999058
    },
    {
      "size": 200000,
      "scenario": "MM_RENDER",
      "label": "micromark (CommonMark)",
      "renderMs": 205.13218330000527
    },
    {
      "size": 200000,
      "scenario": "RM_RENDER",
      "label": "remark+rehype",
      "renderMs": 411.96402499999965
    },
    {
      "size": 500000,
      "scenario": "EX_RENDER",
      "label": "markdown-exit",
      "renderMs": 41.827437500003725
    },
    {
      "size": 500000,
      "scenario": "TS_RENDER",
      "label": "markdown-it-ts.render",
      "renderMs": 31.79595299999346
    },
    {
      "size": 500000,
      "scenario": "MD_RENDER",
      "label": "markdown-it.render",
      "renderMs": 36.19163549999939
    },
    {
      "size": 1000000,
      "scenario": "TS_RENDER",
      "label": "markdown-it-ts.render",
      "renderMs": 61.719187500013504
    },
    {
      "size": 1000000,
      "scenario": "MD_RENDER",
      "label": "markdown-it.render",
      "renderMs": 71.2495625000156
    },
    {
      "size": 1000000,
      "scenario": "EX_RENDER",
      "label": "markdown-exit",
      "renderMs": 87.00337500000023
    }
  ]
}